{
  "comment:0": "NOTE: THIS FILE IS GENERATED. DO NOT EDIT.",
  "comment:1": "Instead modify 'lib/libraries.yaml' and follow the instructions therein.",
  "none": {
    "libraries": {}
  },
  "Client-server APi": {
    "libraries": {
      "client_entry": {
        "uri": "source/client_server_api/client_entry.dart"
      },
      "client_plan": {
        "uri": "source/client_server_api/client_plan.dart"
      },
      "service_entry": {
        "uri": "source/client_server_api/service_entry.dart"
      }
    }
  }
}