[{"name":"Journal","qualifiedName":"Journal.Journal","href":"Journal/Journal-class.html","type":"class","categories":["Client-Server API","Journal"]},{"name":"AddDepartmentScreen","qualifiedName":"add_department_screen.AddDepartmentScreen","href":"source_screens_department_related_add_department_screen/AddDepartmentScreen-class.html","type":"class","categories":["UI WorkerProfiles"]},{"name":"AllServicesOfClientScreen","qualifiedName":"all_services_of_client.AllServicesOfClientScreen","href":"source_screens_service_related_all_services_of_client/AllServicesOfClientScreen-class.html","type":"class","categories":["UI Services"]},{"name":"AppRoot","qualifiedName":"app_root.AppRoot","href":"app_root/AppRoot-class.html","type":"class","categories":["UI Root"]},{"name":"ArchiveMaterialApp","qualifiedName":"app_root.ArchiveMaterialApp","href":"app_root/ArchiveMaterialApp-class.html","type":"class","categories":["UI Root"]},{"name":"MainMaterialApp","qualifiedName":"app_root.MainMaterialApp","href":"app_root/MainMaterialApp-class.html","type":"class","categories":["UI Root"]},{"name":"TakeProofPictureScreen","qualifiedName":"camera.TakeProofPictureScreen","href":"source_screens_service_related_camera/TakeProofPictureScreen-class.html","type":"class","categories":["UI Services"]},{"name":"ClientEntry","qualifiedName":"client_entry.ClientEntry","href":"source_client_server_api_client_entry/ClientEntry-class.html","type":"class","categories":["Client-Server API"]},{"name":"ClientPlan","qualifiedName":"client_plan.ClientPlan","href":"source_client_server_api_client_plan/ClientPlan-class.html","type":"class","categories":["Client-Server API"]},{"name":"ClientProfile","qualifiedName":"client_profile.ClientProfile","href":"source_data_models_client_profile/ClientProfile-class.html","type":"class","categories":["Data Models"]},{"name":"ClientService","qualifiedName":"client_service.ClientService","href":"source_data_models_client_service/ClientService-class.html","type":"class","categories":["Data Models"]},{"name":"ClientServiceAt","qualifiedName":"client_service_at.ClientServiceAt","href":"source_data_models_client_service_at/ClientServiceAt-class.html","type":"class","categories":["Data Models"]},{"name":"AddButton","qualifiedName":"client_service_screen.AddButton","href":"source_screens_service_related_client_service_screen/AddButton-class.html","type":"class","categories":["UI Services"]},{"name":"ClientServiceScreen","qualifiedName":"client_service_screen.ClientServiceScreen","href":"source_screens_service_related_client_service_screen/ClientServiceScreen-class.html","type":"class","categories":["UI Services"]},{"name":"DeleteButton","qualifiedName":"client_service_screen.DeleteButton","href":"source_screens_service_related_client_service_screen/DeleteButton-class.html","type":"class","categories":["UI Services"]},{"name":"ClientServicesListScreen","qualifiedName":"client_services_list_screen.ClientServicesListScreen","href":"source_screens_service_related_client_services_list_screen/ClientServicesListScreen-class.html","type":"class","categories":["UI Services"]},{"name":"datesInArchive","qualifiedName":"controller_dates_in_archive.datesInArchive","href":"source_providers_controller_dates_in_archive/datesInArchive.html","type":"top-level property","categories":["Providers"]},{"name":"datesInArchiveController","qualifiedName":"controller_dates_in_archive.datesInArchiveController","href":"source_providers_controller_dates_in_archive/datesInArchiveController.html","type":"top-level property","categories":["Controllers","Providers"]},{"name":"datesInArchiveOfProfile","qualifiedName":"controller_dates_in_archive.datesInArchiveOfProfile","href":"source_providers_controller_dates_in_archive/datesInArchiveOfProfile.html","type":"top-level property","categories":["Providers"]},{"name":"workerProfiles","qualifiedName":"controller_of_worker_profiles_list.workerProfiles","href":"source_providers_controller_of_worker_profiles_list/workerProfiles.html","type":"top-level property","categories":["Controllers","Providers"]},{"name":"DeleteDepartmentScreen","qualifiedName":"delete_department_screen.DeleteDepartmentScreen","href":"source_screens_department_related_delete_department_screen/DeleteDepartmentScreen-class.html","type":"class","categories":["UI WorkerProfiles"]},{"name":"DateTimeExtensions","qualifiedName":"global_helpers.DateTimeExtensions","href":"source_global_helpers/DateTimeExtensions.html","type":"extension","categories":["Universal_helpers"]},{"name":"httpHeaders","qualifiedName":"global_helpers.httpHeaders","href":"source_global_helpers/httpHeaders-constant.html","type":"top-level constant","categories":["Client-Server API"]},{"name":"HomePage","qualifiedName":"home_screen.HomePage","href":"source_screens_department_related_home_screen/HomePage-class.html","type":"class","categories":["UI WorkerProfiles"]},{"name":"JournalArchive","qualifiedName":"journal_archive.JournalArchive","href":"source_journal_archive_journal_archive/JournalArchive-class.html","type":"class","categories":["Journal"]},{"name":"JournalArchiveAll","qualifiedName":"journal_archive.JournalArchiveAll","href":"source_journal_archive_journal_archive/JournalArchiveAll-class.html","type":"class","categories":["Journal"]},{"name":"ClientScreen","qualifiedName":"list_clients_screen.ClientScreen","href":"source_screens_department_related_list_clients_screen/ClientScreen-class.html","type":"class","categories":["UI WorkerProfiles"]},{"name":"ListOfProfiles","qualifiedName":"list_profiles.ListOfProfiles","href":"source_screens_department_related_list_profiles/ListOfProfiles-class.html","type":"class","categories":["UI WorkerProfiles"]},{"name":"init","qualifiedName":"main.init","href":"main/init.html","type":"function","categories":["UI Root"]},{"name":"locator","qualifiedName":"main.locator","href":"main/locator.html","type":"top-level property","categories":["UI Root"]},{"name":"log","qualifiedName":"main.log","href":"main/log.html","type":"top-level property","categories":["UI Root"]},{"name":"main","qualifiedName":"main.main","href":"main/main.html","type":"function","categories":["About","UI Root"]},{"name":"ProofEntry","qualifiedName":"proof_list.ProofEntry","href":"source_data_models_proof_list/ProofEntry-class.html","type":"class","categories":["Data Models"]},{"name":"ProofList","qualifiedName":"proof_list.ProofList","href":"source_data_models_proof_list/ProofList-class.html","type":"class","categories":["Client-Server API","Data Models"]},{"name":"journalOfClient","qualifiedName":"provider_of_journal.journalOfClient","href":"source_providers_provider_of_journal/journalOfClient.html","type":"top-level property","categories":["Providers"]},{"name":"journalOfWorker","qualifiedName":"provider_of_journal.journalOfWorker","href":"source_providers_provider_of_journal/journalOfWorker.html","type":"top-level property","categories":["Providers"]},{"name":"archiveDate","qualifiedName":"providers_of_app_state.archiveDate","href":"source_providers_providers_of_app_state/archiveDate.html","type":"top-level property","categories":["Providers"]},{"name":"isArchive","qualifiedName":"providers_of_app_state.isArchive","href":"source_providers_providers_of_app_state/isArchive.html","type":"top-level property","categories":["Providers"]},{"name":"lastApiKey","qualifiedName":"providers_of_app_state.lastApiKey","href":"source_providers_providers_of_app_state/lastApiKey.html","type":"top-level property","categories":["Providers"]},{"name":"lastClient","qualifiedName":"providers_of_app_state.lastClient","href":"source_providers_providers_of_app_state/lastClient.html","type":"top-level property","categories":["Providers"]},{"name":"lastClientId","qualifiedName":"providers_of_app_state.lastClientId","href":"source_providers_providers_of_app_state/lastClientId.html","type":"top-level property","categories":["Providers"]},{"name":"lastClientService","qualifiedName":"providers_of_app_state.lastClientService","href":"source_providers_providers_of_app_state/lastClientService.html","type":"top-level property","categories":["Providers"]},{"name":"lastClientServiceId","qualifiedName":"providers_of_app_state.lastClientServiceId","href":"source_providers_providers_of_app_state/lastClientServiceId.html","type":"top-level property","categories":["Providers"]},{"name":"lastServiceAt","qualifiedName":"providers_of_app_state.lastServiceAt","href":"source_providers_providers_of_app_state/lastServiceAt.html","type":"top-level property","categories":["Providers"]},{"name":"lastUsed","qualifiedName":"providers_of_app_state.lastUsed","href":"source_providers_providers_of_app_state/lastUsed.html","type":"top-level property","categories":["Providers"]},{"name":"lastWorkerProfile","qualifiedName":"providers_of_app_state.lastWorkerProfile","href":"source_providers_providers_of_app_state/lastWorkerProfile.html","type":"top-level property","categories":["Providers"]},{"name":"hiveArchiveLimit","qualifiedName":"providers_of_settings.hiveArchiveLimit","href":"source_providers_providers_of_settings/hiveArchiveLimit.html","type":"top-level property","categories":["Providers"]},{"name":"serviceCardSize","qualifiedName":"providers_of_settings.serviceCardSize","href":"source_providers_providers_of_settings/serviceCardSize.html","type":"top-level property","categories":["Providers"]},{"name":"tileTypeProvider","qualifiedName":"providers_of_settings.tileTypeProvider","href":"source_providers_providers_of_settings/tileTypeProvider.html","type":"top-level property","categories":["Providers"]},{"name":"QRScanScreen","qualifiedName":"qr_scan_screen.QRScanScreen","href":"source_screens_department_related_qr_scan_screen/QRScanScreen-class.html","type":"class","categories":["UI WorkerProfiles"]},{"name":"servicesOfClient","qualifiedName":"repository_of_client.servicesOfClient","href":"source_providers_repository_of_client/servicesOfClient.html","type":"top-level property","categories":["Providers"]},{"name":"httpClientProvider","qualifiedName":"repository_of_http_data.httpClientProvider","href":"source_providers_repository_of_http_data/httpClientProvider.html","type":"top-level property","categories":["Providers"]},{"name":"httpDataProvider","qualifiedName":"repository_of_http_data.httpDataProvider","href":"source_providers_repository_of_http_data/httpDataProvider.html","type":"top-level property","categories":["Providers"]},{"name":"planOfWorkerSyncDate","qualifiedName":"repository_of_http_data.planOfWorkerSyncDate","href":"source_providers_repository_of_http_data/planOfWorkerSyncDate.html","type":"top-level property","categories":["Providers"]},{"name":"servicesOfWorkerSyncDate","qualifiedName":"repository_of_http_data.servicesOfWorkerSyncDate","href":"source_providers_repository_of_http_data/servicesOfWorkerSyncDate.html","type":"top-level property","categories":["Providers"]},{"name":"RecorderState","qualifiedName":"repository_of_prooflist.RecorderState","href":"source_providers_repository_of_prooflist/RecorderState.html","type":"enum","categories":["Providers"]},{"name":"groupsOfProof","qualifiedName":"repository_of_prooflist.groupsOfProof","href":"source_providers_repository_of_prooflist/groupsOfProof.html","type":"top-level property","categories":["Providers"]},{"name":"proofAtDate","qualifiedName":"repository_of_prooflist.proofAtDate","href":"source_providers_repository_of_prooflist/proofAtDate.html","type":"top-level property","categories":["Providers"]},{"name":"proofRecorder","qualifiedName":"repository_of_prooflist.proofRecorder","href":"source_providers_repository_of_prooflist/proofRecorder.html","type":"top-level property","categories":["Controllers","Providers"]},{"name":"proofRecorderState","qualifiedName":"repository_of_prooflist.proofRecorderState","href":"source_providers_repository_of_prooflist/proofRecorderState.html","type":"top-level property","categories":["Providers"]},{"name":"servProofAtDate","qualifiedName":"repository_of_prooflist.servProofAtDate","href":"source_providers_repository_of_prooflist/servProofAtDate.html","type":"top-level property","categories":["Providers"]},{"name":"groupsOfService","qualifiedName":"repository_of_service.groupsOfService","href":"source_providers_repository_of_service/groupsOfService.html","type":"top-level property","categories":["Providers"]},{"name":"listDoneProgressErrorOfService","qualifiedName":"repository_of_service.listDoneProgressErrorOfService","href":"source_providers_repository_of_service/listDoneProgressErrorOfService.html","type":"top-level property","categories":["Providers"]},{"name":"clientsOfWorker","qualifiedName":"repository_of_worker.clientsOfWorker","href":"source_providers_repository_of_worker/clientsOfWorker.html","type":"top-level property","categories":["Providers"]},{"name":"planOfWorker","qualifiedName":"repository_of_worker.planOfWorker","href":"source_providers_repository_of_worker/planOfWorker.html","type":"top-level property","categories":["Providers"]},{"name":"servicesOfWorker","qualifiedName":"repository_of_worker.servicesOfWorker","href":"source_providers_repository_of_worker/servicesOfWorker.html","type":"top-level property","categories":["Providers"]},{"name":"ServiceCard","qualifiedName":"service_card.ServiceCard","href":"source_screens_service_related_service_card/ServiceCard-class.html","type":"class","categories":["UI Services"]},{"name":"ServiceCardState","qualifiedName":"service_card_state.ServiceCardState","href":"source_screens_service_related_service_card_state/ServiceCardState-class.html","type":"class","categories":["UI Services"]},{"name":"ServiceCardSquareView","qualifiedName":"service_card_view.ServiceCardSquareView","href":"source_screens_service_related_service_card_view/ServiceCardSquareView-class.html","type":"class","categories":["UI Services"]},{"name":"ServiceCardTileView","qualifiedName":"service_card_view.ServiceCardTileView","href":"source_screens_service_related_service_card_view/ServiceCardTileView-class.html","type":"class","categories":["UI Services"]},{"name":"ServiceCardView","qualifiedName":"service_card_view.ServiceCardView","href":"source_screens_service_related_service_card_view/ServiceCardView-class.html","type":"class","categories":["UI Services"]},{"name":"ServiceEntry","qualifiedName":"service_entry.ServiceEntry","href":"source_client_server_api_service_entry/ServiceEntry-class.html","type":"class","categories":["Client-Server API"]},{"name":"ServiceOfJournal","qualifiedName":"service_of_journal.ServiceOfJournal","href":"source_journal_service_of_journal/ServiceOfJournal-class.html","type":"class","categories":["Client-Server API","Journal"]},{"name":"AddProofButton","qualifiedName":"service_proofs_list.AddProofButton","href":"source_screens_service_related_service_proofs_list/AddProofButton-class.html","type":"class","categories":["UI Proofs"]},{"name":"ImageOrButtonAdd","qualifiedName":"service_proofs_list.ImageOrButtonAdd","href":"source_screens_service_related_service_proofs_list/ImageOrButtonAdd-class.html","type":"class","categories":["UI Proofs"]},{"name":"ProofListBuilder","qualifiedName":"service_proofs_list.ProofListBuilder","href":"source_screens_service_related_service_proofs_list/ProofListBuilder-class.html","type":"class","categories":["UI Proofs"]},{"name":"ServiceProofList","qualifiedName":"service_proofs_list.ServiceProofList","href":"source_screens_service_related_service_proofs_list/ServiceProofList-class.html","type":"class","categories":["UI Proofs","UI Services"]},{"name":"ServiceState","qualifiedName":"service_state.ServiceState","href":"source_journal_service_state/ServiceState.html","type":"enum","categories":["Journal"]},{"name":"standardTheme","qualifiedName":"themes_data.standardTheme","href":"themes_data/standardTheme.html","type":"top-level property","categories":["UI Root"]},{"name":"WorkerKey","qualifiedName":"worker_key.WorkerKey","href":"source_client_server_api_worker_key/WorkerKey-class.html","type":"class","categories":["Client-Server API"]},{"name":"WorkerProfile","qualifiedName":"worker_profile.WorkerProfile","href":"source_data_models_worker_profile/WorkerProfile-class.html","type":"class","categories":["Data Models"]}]
